blitzbeaver-1.0.0.dist-info/METADATA
blitzbeaver-1.0.0.dist-info/WHEEL
blitzbeaver-1.0.0.dist-info/licenses/LICENSE
blitzbeaver/tracking_graph.py
blitzbeaver/tracking.py
blitzbeaver/serialization.py
blitzbeaver/exceptions.py
blitzbeaver/blitzbeaver.pyi
blitzbeaver/logger.py
blitzbeaver/literals.py
blitzbeaver/__init__.py
blitzbeaver/config.py
blitzbeaver/beaver_file.py
blitzbeaver/normalization.py
blitzbeaver/blitzbeaver.cpython-311-x86_64-linux-gnu.so
blitzbeaver-1.0.0.dist-info/RECORD
