Metadata-Version: 2.4
Name: blitzbeaver
Version: 1.0.0
Classifier: Programming Language :: Rust
Classifier: Programming Language :: Python :: Implementation :: CPython
Requires-Dist: polars>=1.19.0,<2
Requires-Dist: pyarrow>=19.0.0,<20.0.0
License-File: LICENSE
Summary: Persons tracking accross historical records.
Author-email: Alexandre Goumaz <alexandre.goumaz@epfl.ch>, Timo Moebel <timo.moebel@epfl.ch>
Requires-Python: >=3.10
Project-URL: Repository, https://github.com/Plouc314/blitzbeaver
